setup.py
faker_extras/__init__.py
faker_extras/alien.py
faker_extras/binary.py
faker_extras/biology.py
faker_extras/chemistry.py
faker_extras/human.py
faker_extras/utils.py
faker_extras.egg-info/PKG-INFO
faker_extras.egg-info/SOURCES.txt
faker_extras.egg-info/dependency_links.txt
faker_extras.egg-info/not-zip-safe
faker_extras.egg-info/requires.txt
faker_extras.egg-info/top_level.txt