Metadata-Version: 1.1
Name: faker-extras
Version: 1.0.2
Summary: An extended set of data providers for the Faker library.
Home-page: https://github.com/christabor/faker_extras
Author: Chris Tabor
Author-email: dxdstudio@gmail.com
License: Apache License 2.0
Keywords: faker_extras,fake data generation,faker,data generator
Platform: UNKNOWN
Classifier: Intended Audience :: Developers
Classifier: Natural Language :: English
Classifier: Operating System :: OS Independent
Classifier: Topic :: Utilities
